<DOMSymbolItem xmlns:xsi="http://www.w3.org/2001/XMLSchema-instance" xmlns="http://ns.adobe.com/xfl/2008/" name="UI/HUDMenu/SafeRect" itemID="5dc1488c-000002c8" lastModified="1573012329">
  <timeline>
    <DOMTimeline name="SafeRect">
      <layers>
        <DOMLayer name="Shape" color="#4F63EF" locked="true" current="true" isSelected="true" autoNamed="false">
          <frames>
            <DOMFrame index="0" keyMode="9728">
              <elements>
                <DOMShape selected="true" isFloating="true">
                  <strokes>
                    <StrokeStyle index="1">
                      <SolidStroke scaleMode="normal">
                        <fill>
                          <SolidColor color="#CC3399"/>
                        </fill>
                      </SolidStroke>
                    </StrokeStyle>
                  </strokes>
                  <edges>
                    <Edge strokeStyle="1" edges="!-11520 -6480S4|11520 -6480!11520 -6480|11520 6480!11520 6480|-11520 6480!-11520 6480|-11520 -6480"/>
                  </edges>
                </DOMShape>
              </elements>
            </DOMFrame>
          </frames>
        </DOMLayer>
      </layers>
    </DOMTimeline>
  </timeline>
</DOMSymbolItem>