<DOMSymbolItem xmlns:xsi="http://www.w3.org/2001/XMLSchema-instance" xmlns="http://ns.adobe.com/xfl/2008/" name="UI/LevelUpMenu/PerkGrid/PerkClips.ART/Symbol 1189" itemID="5dc12b90-000001e2" symbolType="graphic" lastModified="1571730685">
  <timeline>
    <DOMTimeline name="Symbol 1189">
      <layers>
        <DOMLayer name="Layer 1" color="#4F4FFF" current="true" isSelected="true">
          <frames>
            <DOMFrame index="0" motionTweenScale="false" keyMode="8192">
              <elements>
                <DOMShape isFloating="true">
                  <fills>
                    <FillStyle index="1">
                      <SolidColor color="#020303"/>
                    </FillStyle>
                    <FillStyle index="2">
                      <SolidColor color="#FEEA30"/>
                    </FillStyle>
                    <FillStyle index="3">
                      <SolidColor color="#FFE1BA"/>
                    </FillStyle>
                    <FillStyle index="4">
                      <SolidColor color="#FBF17A"/>
                    </FillStyle>
                    <FillStyle index="5">
                      <SolidColor color="#0067B1"/>
                    </FillStyle>
                    <FillStyle index="6">
                      <SolidColor color="#8B5D28"/>
                    </FillStyle>
                    <FillStyle index="7">
                      <SolidColor color="#FAF1D5"/>
                    </FillStyle>
                    <FillStyle index="8">
                      <SolidColor color="#D49758"/>
                    </FillStyle>
                  </fills>
                  <edges>
                    <Edge fillStyle1="1" edges="!355 -3223[399 -3164 427 -3105!427 -3105[449 -3055 451 -2964!451 -2964[452 -2884 438 -2816!438 -2816[426 -2753 404 -2690!404 -2690[383 -2626 365 -2597!365 -2597|358 -2587!358 -2587[430 -2518 381 -2416!381 -2416[334 -2317 248 -2317!248
 -2317|237 -2318!237 -2318[217 -2282 185 -2244!185 -2244|126 -2177!126 -2177[243 -2109 406 -1959!406 -1959[615 -1768 720 -1593!720 -1593[839 -1394 929 -1156!929 -1156[984 -1009 1016 -885!1016 -885|1020 -857!1020 -857|1020 -827!1020 -827
|1020 -826!1020 -826[1065 -741 1074 -666!1074 -666[1094 -508 1059 -385!1059 -385[1048 -342 1019 -318!1019 -318[997 -300 970 -295!970 -295[918 -199 863 -187!863 -187|839 -186!839 -186[780 -52 710 -76!710 -76[675 -87 669 -141!669 -141[666
 -175 674 -249!674 -249|676 -269!676 -269|687 -422!687 -422|641 -404!641 -404[544 -372 499 -404!499 -404[477 -419 477 -445!477 -445|477 -450!477 -450[480 -468 493 -481!493 -481|524 -503!524 -503[567 -530 593 -555!593 -555[617 -582 635
 -627!635 -627[545 -826 421 -985!421 -985|419 -959!419 -959[416 -868 431 -787!431 -787|429 -764!429 -764|431 -759!431 -759[446 -617 429 -456!429 -456[411 -266 348 -42!348 -42|336 3!336 3|337 4!337 4[522 145 667 452!667 452[689 499 695
 527!695 527[705 566 696 606!696 606[663 763 561 887!561 887[473 995 345 1052!345 1052[183 1125 101 1023!101 1023[47 954 95 841!95 841[118 786 199 672!199 672|122 578!122 578|64 693!64 693[-23 857 -82 942!-82 942[-179 1080 -286 1142!-286
 1142[-378 1196 -496 1133!-496 1133[-567 1093 -672 992!-672 992[-794 873 -872 753!-872 753|-928 655!-928 655[-956 596 -957 547!-957 547[-959 490 -901 467!-901 467[-855 448 -793 454!-793 454[-685 463 -580 546!-580 546[-542 495 -515 417
!-515 417[-496 365 -476 277!-476 277[-441 126 -417 -70!-417 -70|-412 -125!-412 -125[-548 -257 -631 -415!-631 -415[-724 -591 -733 -763!-733 -763|-733 -765!-733 -765[-737 -784 -733 -819!-733 -819[-726 -854 -726 -867!-726 -867[-720 -964
 -733 -1058!-733 -1058|-740 -1096!-740 -1096[-865 -968 -941 -850!-941 -850|-941 -849!-941 -849|-952 -843!-952 -843|-957 -796!-957 -796[-964 -750 -1000 -703!-1000 -703[-959 -655 -934 -609!-934 -609[-890 -534 -909 -499!-909 -499[-923 -475
 -946 -470!-946 -470|-971 -469!-971 -469|-970 -452!-970 -452[-971 -418 -994 -404!-994 -404|-1039 -400!-1039 -400[-1053 -364 -1078 -348!-1078 -348[-1119 -323 -1183 -357!-1183 -357|-1248 -405!-1248 -405[-1288 -449 -1324 -513!-1324 -513
[-1397 -639 -1398 -753!-1398 -753[-1398 -900 -1266 -1116!-1266 -1116|-1267 -1140!-1267 -1140|-1262 -1169!-1262 -1169|-1253 -1196!-1253 -1196[-1197 -1314 -1117 -1446!-1117 -1446[-983 -1662 -828 -1835!-828 -1835[-735 -1940 -618 -2026!-618
 -2026|-613 -2032!-613 -2032|-612 -2031!-612 -2031|-586 -2050!-586 -2050[-746 -2164 -809 -2366!-809 -2366[-869 -2563 -813 -2763!-813 -2763|-783 -2851!-783 -2851[-817 -2899 -830 -2936!-830 -2936[-848 -2986 -834 -3039!-834 -3039[-825 -3074
 -808 -3098!-808 -3098[-855 -3181 -826 -3262!-826 -3262[-809 -3309 -756 -3350!-756 -3350[-712 -3384 -693 -3384!-693 -3384|-690 -3384!-690 -3384[-688 -3381 -703 -3345!-703 -3345[-719 -3307 -709 -3292!-709 -3292[-696 -3269 -655 -3269!-655
 -3269[-627 -3269 -604 -3286!-604 -3286[-587 -3298 -560 -3335!-560 -3335|-518 -3385!-518 -3385[-489 -3411 -453 -3420!-453 -3420|-370 -3429!-370 -3429[-313 -3436 -294 -3461!-294 -3461|-241 -3526!-241 -3526[-209 -3558 -179 -3561!-179 -3561
|-167 -3562!-167 -3562[-126 -3562 -77 -3528!-77 -3528|-24 -3487!-24 -3487|40 -3477!40 -3477|115 -3462!115 -3462[140 -3453 183 -3387!183 -3387[226 -3321 243 -3317!243 -3317[294 -3303 355 -3223"/>
                    <Edge fillStyle0="1" fillStyle1="2" edges="
!172 -3358|234 -3282!234 -3282[275 -3264 320 -3199!320 -3199[352 -3154 376 -3100!376 -3100[417 -3007 392 -2856!392 -2856[379 -2781 358 -2724!358 -2724[339 -2813 275 -2875!275 -2875[246 -2905 192 -2943!192 -2943[227 -2968 251 -2998!251
 -2998[283 -3038 278 -3068!278 -3068[272 -3109 249 -3140!249 -3140[216 -3180 160 -3180!160 -3180|137 -3178!137 -3178[116 -3175 65 -3152!65 -3152[17 -3130 0 -3130!0 -3130|-6 -3132!-6 -3132[-13 -3134 -77 -3202!-77 -3202[-138 -3268 -175
 -3268!-175 -3268|-193 -3265!-193 -3265|-264 -3220!-264 -3220|-309 -3194!-309 -3194[-329 -3181 -341 -3181!-341 -3181|-354 -3184!-354 -3184|-383 -3199!-383 -3199[-423 -3219 -439 -3219!-439 -3219[-460 -3219 -487 -3204!-487 -3204[-508 -3192
 -557 -3130!-557 -3130|-608 -3067!-608 -3067[-652 -3030 -694 -3030!-694 -3030[-723 -3030 -742 -3049!-742 -3049[-781 -3086 -796 -3146!-796 -3146[-809 -3206 -793 -3251!-793 -3251[-780 -3286 -753 -3314!-753 -3314[-757 -3273 -731 -3253!-731
 -3253[-701 -3230 -664 -3230!-664 -3230[-610 -3230 -572 -3273!-572 -3273[-477 -3382 -441 -3392!-441 -3392|-415 -3395!-415 -3395|-365 -3386!-365 -3386[-335 -3375 -323 -3375!-323 -3375[-307 -3375 -296 -3387!-296 -3387[-284 -3397 -258 -3439
!-258 -3439[-204 -3524 -178 -3529!-178 -3529|-172 -3529!-172 -3529[-140 -3529 -96 -3498!-96 -3498|-67 -3476!-67 -3476[-51 -3463 -35 -3458!-35 -3458[24 -3438 58 -3433!58 -3433[120 -3425 172 -3358"/>
                    <Edge fillStyle0="3" fillStyle1="1" edges="
!44 -3118[10 -3105 -12 -3105!-12 -3105[-42 -3105 -60 -3126!-60 -3126[-120 -3196 -193 -3196!-193 -3196[-222 -3196 -244 -3183!-244 -3183[-300 -3153 -334 -3153!-334 -3153|-375 -3161!-375 -3161[-416 -3188 -447 -3188!-447 -3188|-468 -3182
!-468 -3182[-484 -3173 -533 -3112!-533 -3112|-586 -3046!-586 -3046[-627 -3011 -668 -3003!-668 -3003[-751 -2867 -777 -2731!-777 -2731[-822 -2513 -732 -2308!-732 -2308[-637 -2093 -443 -2007!-443 -2007[-332 -1959 -247 -1959!-247 -1959|-202
 -1964!-202 -1964|-177 -1967!-177 -1967|-173 -1965!-173 -1965[-170 -1956 -218 -1941!-218 -1941[-264 -1926 -287 -1926!-287 -1926|-293 -1926!-293 -1926[-267 -1911 -228 -1911!-228 -1911[-140 -1911 -47 -1970!-47 -1970[52 -2034 61 -2113!61
 -2113[4 -2072 -41 -2072!-41 -2072[-54 -2072 -55 -2077!-55 -2077[-56 -2083 -42 -2092!-42 -2092[93 -2181 190 -2352!190 -2352|206 -2351!206 -2351[296 -2351 331 -2436!331 -2436[367 -2522 292 -2579!292 -2579[281 -2596 296 -2604!296 -2604
|313 -2609!313 -2609|317 -2618!317 -2618|223 -2743!223 -2743|170 -2782!170 -2782[155 -2791 155 -2803!155 -2803[156 -2815 165 -2815!165 -2815|170 -2814!170 -2814[200 -2803 241 -2763!241 -2763[292 -2711 329 -2631!329 -2631|330 -2630!330
 -2630|335 -2653!335 -2653[282 -2759 234 -2804!234 -2804|179 -2854!179 -2854|153 -2876!153 -2876[144 -2882 146 -2890!146 -2890[148 -2899 159 -2899!159 -2899|168 -2896!168 -2896[191 -2889 253 -2821!253 -2821[308 -2756 337 -2684!337 -2684
[339 -2783 255 -2863!255 -2863[219 -2895 155 -2933!155 -2933[141 -2941 147 -2953!147 -2953|157 -2962!157 -2962[242 -3010 220 -3076!220 -3076[200 -3139 142 -3139!142 -3139|136 -3138!136 -3138|44 -3118"/>
                    <Edge fillStyle0="1" fillStyle1="3" edges="
!169 -2731[160 -2731 157 -2722!157 -2722[154 -2712 165 -2704!165 -2704|207 -2676!207 -2676|235 -2645!235 -2645|257 -2625!257 -2625|261 -2630!261 -2630[263 -2638 250 -2658!250 -2658|224 -2694!224 -2694[203 -2716 172 -2731!172 -2731|169
 -2731!193 -2591[195 -2580 207 -2580!207 -2580[219 -2580 218 -2597!218 -2597[217 -2613 202 -2629!202 -2629[189 -2643 176 -2649!176 -2649|171 -2651!171 -2651[162 -2651 159 -2641!159 -2641[156 -2632 164 -2626!164 -2626|178 -2615!178 -2615
|193 -2591"/>
                    <Edge fillStyle0="4" fillStyle1="1" edges="
!173 -2087|117 -2129!117 -2129[100 -2016 -11 -1938!-11 -1938[-117 -1864 -239 -1864!-239 -1864[-307 -1864 -359 -1892!-359 -1892[-417 -1921 -446 -1978!-446 -1978[-488 -1994 -536 -2019!-536 -2019|-608 -1962!-608 -1962[-623 -1930 -616 -1900
!-616 -1900[-600 -1838 -476 -1798!-476 -1798|-472 -1796!-472 -1796[-451 -1785 -453 -1742!-453 -1742[-454 -1710 -472 -1610!-472 -1610[-498 -1467 -497 -1419!-497 -1419[-496 -1277 -468 -1042!-468 -1042|-456 -903!-456 -903[-454 -860 -466
 -846!-466 -846[-476 -837 -490 -837!-490 -837[-595 -837 -683 -910!-683 -910|-689 -763!-689 -763[-596 -683 -465 -638!-465 -638[-226 -555 52 -619!52 -619[203 -652 294 -710!294 -710[349 -746 374 -771!374 -771|388 -795!388 -795|383 -822!383
 -822[373 -881 375 -951!375 -951[303 -905 203 -871!203 -871[59 -821 -115 -807!-115 -807|-119 -806!-119 -806[-138 -806 -153 -849!-153 -849[-176 -916 -195 -1095!-195 -1095[-215 -1300 -213 -1460!-213 -1460[-208 -1745 -128 -1756!-128 -1756
[-50 -1763 27 -1808!27 -1808[104 -1852 146 -1915!146 -1915[162 -1938 171 -1991!171 -1991[180 -2045 173 -2087"/>
                    <Edge fillStyle0="5" fillStyle1="1" edges="
!48 -1771[-37 -1721 -122 -1714!-122 -1714[-132 -1714 -142 -1686!-142 -1686[-185 -1578 -164 -1236!-164 -1236[-143 -915 -109 -850!-109 -850[79 -865 230 -926!230 -926[320 -963 377 -1005!377 -1005|380 -1035!380 -1035[288 -1140 153 -1252!153
 -1252|34 -1344!34 -1344|41 -1385!41 -1385|195 -1279!195 -1279[366 -1150 464 -1027!464 -1027[555 -911 628 -769!628 -769[669 -688 690 -629!690 -629[729 -615 825 -641!825 -641[888 -659 930 -731!930 -731[955 -771 966 -818!966 -818[969 -832
 961 -864!961 -864|958 -873!958 -873[925 -999 873 -1138!873 -1138[785 -1371 669 -1562!669 -1562[572 -1723 397 -1898!397 -1898[323 -1971 225 -2048!225 -2048[236 -1969 181 -1890!181 -1890[133 -1821 48 -1771"/>
                    <Edge fillStyle0="3" fillStyle1="1" edges="
!623 -526[589 -492 546 -467!546 -467[529 -458 520 -445!520 -445[510 -424 542 -419!542 -419[573 -413 614 -427!614 -427|687 -460!687 -460[727 -479 729 -475!729 -475|731 -464!731 -464|727 -389!727 -389|718 -264!718 -264|715 -245!715 -245
[703 -122 724 -116!724 -116[756 -105 797 -216!797 -216|829 -362!829 -362[848 -470 851 -470!851 -470[874 -463 858 -347!858 -347|839 -229!839 -229[846 -225 855 -229!855 -229[913 -249 944 -389!944 -389[965 -519 971 -513!971 -513[988 -497
 976 -415!976 -415|965 -338!965 -338[1003 -338 1019 -395!1019 -395[1052 -514 1032 -661!1032 -661[1025 -708 1001 -767!1001 -767[945 -629 831 -597!831 -597[722 -565 665 -590!665 -590[648 -552 623 -526"/>
                    <Edge fillStyle0="5" fillStyle1="1" edges="
!7 -556[-181 -527 -358 -566!-358 -566[-452 -586 -526 -621!-526 -621[-624 -666 -687 -714!-687 -714[-671 -567 -592 -420!-592 -420[-519 -282 -407 -170!-407 -170[-389 -358 -385 -501!-385 -501[-385 -515 -370 -512!-370 -512[-360 -510 -352 -499
!-352 -499[-342 -490 -342 -480!-342 -480[-351 -241 -380 -8!-380 -8[-410 220 -447 350!-447 350[-485 492 -533 564!-533 564[-414 600 -307 715!-307 715[-220 811 -152 944!-152 944[-82 855 -17 740!-17 740[176 398 293 -15!293 -15[347 -211 372
 -361!372 -361[402 -553 393 -716!393 -716|342 -680!342 -680[196 -587 7 -556!602 406[537 287 482 209!482 209[406 104 325 41!325 41[249 304 138 542!138 542|236 659!236 659[357 720 473 639!473 639[579 566 613 435!613 435|615 430!615 430
|602 406"/>
                    <Edge fillStyle0="6" fillStyle1="1" edges="
!119 917[102 976 137 1010!137 1010[201 1073 367 983!367 983[504 907 582 768!582 768|636 658!636 658[664 587 658 538!658 538|645 489!645 489[597 623 486 690!486 690[364 762 238 704!238 704|192 775!192 775[256 778 331 815!331 815[349 823
 347 845!347 845[346 865 325 854!325 854[232 808 164 822!164 822[128 886 119 917"/>
                    <Edge fillStyle0="1" fillStyle1="2" edges="
!-708 -3005|-769 -2888!-769 -2888[-795 -2932 -800 -2960!-800 -2960[-806 -2993 -798 -3018!-798 -3018[-791 -3043 -776 -3043!-776 -3043|-758 -3033!-758 -3033[-736 -3013 -708 -3005"/>
                    <Edge fillStyle0="1" fillStyle1="3" edges="
!-543 -2996[-544 -3012 -559 -3012!-559 -3012|-570 -3008!-570 -3008|-650 -2958!-650 -2958|-659 -2948!-659 -2948|-649 -2944!-649 -2944|-561 -2948!-561 -2948[-551 -2948 -544 -2957!-544 -2957[-538 -2964 -540 -2975!-540 -2975|-543 -2996!-173
 -3002[-188 -2981 -185 -2975!-185 -2975|-165 -2966!-165 -2966|-124 -2949!-124 -2949|-80 -2923!-80 -2923[-56 -2909 -48 -2909!-48 -2909|-47 -2909!-47 -2909[-41 -2936 -85 -2985!-85 -2985|-132 -3030!-132 -3030|-142 -3033!-142 -3033[-153 -3033
 -158 -3022!-158 -3022|-173 -3002!-135 -2819[-146 -2840 -161 -2841!-161 -2841[-177 -2841 -189 -2820!-189 -2820[-201 -2800 -202 -2770!-202 -2770[-203 -2741 -192 -2720!-192 -2720[-182 -2698 -166 -2697!-166 -2697|-165 -2697!-165 -2697[-149
 -2697 -137 -2719!-137 -2719[-126 -2739 -124 -2768!-124 -2768[-123 -2798 -135 -2819!-378 -2836|-379 -2836!-379 -2836[-392 -2836 -397 -2818!-397 -2818|-441 -2733!-441 -2733[-461 -2699 -523 -2622!-523 -2622[-537 -2607 -525 -2588!-525 -2588
|-478 -2518!-478 -2518[-466 -2506 -450 -2506!-450 -2506|-427 -2512!-427 -2512[-419 -2513 -416 -2521!-416 -2521[-413 -2527 -419 -2534!-419 -2534|-458 -2586!-458 -2586[-471 -2603 -460 -2622!-460 -2622|-416 -2707!-416 -2707[-390 -2758 -373
 -2814!-373 -2814[-368 -2834 -378 -2836!-209 -2515|-196 -2482!-196 -2482[-193 -2475 -201 -2465!-201 -2465[-207 -2456 -216 -2454!-216 -2454[-361 -2400 -432 -2392!-432 -2392|-461 -2390!-461 -2390|-571 -2401!-571 -2401|-627 -2411!-627 -2411
|-642 -2420!-642 -2420[-648 -2427 -647 -2436!-647 -2436|-646 -2451!-646 -2451[-646 -2461 -650 -2461!-650 -2461|-659 -2456!-659 -2456|-698 -2408!-698 -2408|-704 -2390!-704 -2390|-700 -2373!-700 -2373|-654 -2303!-654 -2303|-647 -2297!-647
 -2297[-644 -2297 -644 -2307!-644 -2307|-644 -2317!-644 -2317[-644 -2333 -629 -2333!-629 -2333|-624 -2333!-624 -2333|-557 -2294!-557 -2294[-477 -2255 -412 -2254!-412 -2254|-411 -2254!-411 -2254[-346 -2254 -240 -2315!-240 -2315|-147 -2377
!-147 -2377|-137 -2378!-137 -2378[-123 -2378 -115 -2366!-115 -2366|-115 -2318!-115 -2318|-105 -2312!-105 -2312[-100 -2312 -99 -2321!-99 -2321|-79 -2418!-79 -2418[-76 -2437 -94 -2450!-94 -2450|-200 -2525!-200 -2525|-207 -2527!-207 -2527
[-214 -2527 -209 -2515!-581 -2817[-592 -2838 -608 -2838!-608 -2838|-609 -2839!-609 -2839[-625 -2839 -636 -2818!-636 -2818[-648 -2798 -649 -2768!-649 -2768[-650 -2738 -640 -2716!-640 -2716[-629 -2695 -613 -2695!-613 -2695|-612 -2695!-612
 -2695[-596 -2695 -585 -2715!-585 -2715[-573 -2737 -572 -2766!-572 -2766[-571 -2796 -581 -2817"/>
                    <Edge fillStyle0="1" fillStyle1="7" edges="
!-499 -2306|-629 -2350!-629 -2350[-644 -2353 -650 -2373!-650 -2373[-654 -2391 -631 -2391!-631 -2391|-628 -2391!-628 -2391|-570 -2381!-570 -2381|-451 -2371!-451 -2371|-422 -2371!-422 -2371[-338 -2379 -207 -2433!-207 -2433|-182 -2437!-182
 -2437[-167 -2437 -154 -2427!-154 -2427[-140 -2417 -149 -2404!-149 -2404[-154 -2395 -166 -2388!-166 -2388[-282 -2327 -326 -2312!-326 -2312[-364 -2298 -432 -2298!-432 -2298|-499 -2306"/>
                    <Edge fillStyle0="1" fillStyle1="3" edges="
!-449 -2185|-422 -2180!-422 -2180|-386 -2185!-386 -2185|-371 -2195!-371 -2195[-365 -2203 -367 -2211!-367 -2211[-370 -2227 -390 -2227!-390 -2227|-394 -2227!-394 -2227|-482 -2217!-482 -2217[-493 -2216 -493 -2211!-493 -2211|-485 -2203!-485
 -2203|-449 -2185"/>
                    <Edge fillStyle0="5" fillStyle1="1" edges="
!-783 -1796[-934 -1629 -1064 -1418!-1064 -1418[-1143 -1289 -1198 -1174!-1198 -1174|-1201 -1165!-1201 -1165[-1217 -1133 -1216 -1121!-1216 -1121[-1214 -1075 -1197 -1029!-1197 -1029[-1170 -950 -1111 -921!-1111 -921[-1024 -877 -981 -883!-981
 -883|-914 -983!-914 -983[-840 -1081 -754 -1166!-754 -1166|-801 -1360!-801 -1360[-829 -1475 -836 -1555!-836 -1555|-782 -1468!-782 -1468[-768 -1390 -727 -1230!-727 -1230[-691 -1084 -685 -996!-685 -996|-684 -968!-684 -968|-625 -919!-625
 -919[-563 -882 -498 -879!-498 -879[-494 -909 -511 -1037!-511 -1037[-538 -1275 -539 -1418!-539 -1418[-540 -1478 -514 -1617!-514 -1617|-500 -1700!-500 -1700[-493 -1746 -496 -1760!-496 -1760[-635 -1805 -657 -1890!-657 -1890|-661 -1918!-661
 -1918[-724 -1863 -783 -1796"/>
                    <Edge fillStyle0="3" fillStyle1="1" edges="
!-995 -838|-1056 -850!-1056 -850[-1061 -761 -1111 -736!-1111 -736|-1097 -648!-1097 -648[-1083 -585 -1082 -555!-1082 -555[-1080 -508 -1104 -491!-1104 -491|-1107 -488!-1107 -488|-1063 -449!-1063 -449[-1033 -429 -1013 -445!-1013 -445[-992
 -463 -1026 -521!-1026 -521[-1063 -586 -1061 -592!-1061 -592|-1059 -592!-1059 -592|-1054 -592!-1054 -592|-1009 -541!-1009 -541[-969 -500 -946 -519!-946 -519[-932 -532 -983 -616!-983 -616|-1046 -708!-1046 -708[-1031 -723 -1017 -750!-1017
 -750|-999 -802!-999 -802|-995 -838!-1125 -877[-1219 -925 -1254 -1052!-1254 -1052[-1356 -872 -1356 -753!-1356 -753[-1355 -669 -1309 -574!-1309 -574[-1279 -512 -1235 -456!-1235 -456|-1217 -434!-1217 -434|-1196 -418!-1196 -418[-1129 -366
 -1100 -385!-1100 -385[-1089 -391 -1086 -406!-1086 -406[-1084 -420 -1089 -428!-1089 -428|-1114 -476!-1114 -476|-1117 -484!-1117 -484[-1148 -475 -1191 -502!-1191 -502[-1274 -551 -1297 -691!-1297 -691[-1315 -799 -1299 -834!-1299 -834[-1292
 -847 -1274 -846!-1274 -846[-1255 -845 -1256 -829!-1256 -829|-1253 -700!-1253 -700[-1237 -580 -1170 -539!-1170 -539[-1138 -520 -1129 -524!-1129 -524[-1117 -533 -1138 -640!-1138 -640|-1159 -765!-1159 -765|-1142 -770!-1142 -770[-1129 -773
 -1117 -787!-1117 -787[-1092 -814 -1092 -862!-1092 -862|-1125 -877"/>
                    <Edge fillStyle0="8" fillStyle1="1" edges="
!-809 495[-885 491 -907 531!-907 531[-932 575 -890 656!-890 656|-817 769!-817 769[-730 893 -623 990!-623 990|-381 880!-381 880|-438 793!-438 793[-508 681 -584 589!-584 589[-639 545 -701 520!-701 520[-754 498 -809 495"/>
                    <Edge fillStyle0="6" fillStyle1="1" edges="
!-316 760[-413 648 -522 611!-522 611[-444 710 -381 815!-381 815|-314 935!-314 935[-274 1018 -277 1077!-277 1077|-202 1003!-202 1003|-177 975!-177 975[-238 850 -316 760"/>
                    <Edge fillStyle0="8" fillStyle1="1" edges="
!-335 1108[-294 1047 -358 922!-358 922|-581 1026!-581 1026|-485 1096!-485 1096[-424 1131 -375 1124!-375 1124|-337 1114!-337 1114|-335 1108"/>
                  </edges>
                </DOMShape>
              </elements>
            </DOMFrame>
          </frames>
        </DOMLayer>
      </layers>
    </DOMTimeline>
  </timeline>
</DOMSymbolItem>