<DOMSymbolItem xmlns:xsi="http://www.w3.org/2001/XMLSchema-instance" xmlns="http://ns.adobe.com/xfl/2008/" name="UI/PowerArmorHUDMenu/Symbol 74" itemID="5dc1239a-0000003d" lastModified="1571730685">
  <timeline>
    <DOMTimeline name="Symbol 74">
      <layers>
        <DOMLayer name="Layer 1" color="#5283FB" current="true" isSelected="true">
          <frames>
            <DOMFrame index="0" keyMode="9728">
              <elements>
                <DOMShape isFloating="true">
                  <fills>
                    <FillStyle index="1">
                      <SolidColor color="#FFFFFF"/>
                    </FillStyle>
                  </fills>
                  <edges>
                    <Edge fillStyle1="1" edges="!60 -60|60 60!60 60|-60 60!-60 60|-60 -60!-60 -60|60 -60"/>
                  </edges>
                </DOMShape>
              </elements>
            </DOMFrame>
          </frames>
        </DOMLayer>
      </layers>
    </DOMTimeline>
  </timeline>
</DOMSymbolItem>