<DOMSymbolItem xmlns:xsi="http://www.w3.org/2001/XMLSchema-instance" xmlns="http://ns.adobe.com/xfl/2008/" name="UI/HUDMenu/HUDNotificationsGroup/TutorialText/TutorialHeads_01" itemID="5dc25f21-000002bf" lastModified="1573019425">
  <timeline>
    <DOMTimeline name="TutorialHeads_01">
      <layers>
        <DOMLayer name="Layer 1" color="#BBCB74" current="true" isSelected="true">
          <frames>
            <DOMFrame index="0" duration="50" keyMode="9728">
              <elements>
                <DOMShape isFloating="true">
                  <fills>
                    <FillStyle index="1">
                      <SolidColor color="#FFFFFF"/>
                    </FillStyle>
                  </fills>
                  <edges>
                    <Edge fillStyle0="1" edges="!1060 161[1065 198 1043 219!1043 219[1018 243 982 245!982 245[932 251 893 211!893 211[797 115 762 110!762 110|738 109!738 109[722 110 692 121!692 121|652 134!652 134[638 134 626 124!626 124|587 79!587 79[529 1 505 0!505 0|499 0!499 0
[471 1 432 34!432 34[422 41 406 56!406 56[392 70 377 76!377 76[324 99 291 106!291 106[232 117 189 184!189 184|136 260!136 260[98 279 60 342!60 342[33 390 16 440!16 440[-17 529 18 670!18 670[34 739 58 791!58 791[68 708 125 642!125 642
|198 574!198 574|140 527!140 527[107 490 109 463!109 463[112 423 132 394!132 394[159 353 212 349!212 349|234 349!234 349[254 350 304 370!304 370[351 386 366 384!366 384|371 384!371 384|434 312!434 312[487 245 522 243!522 243|538 245!538
 245|609 282!609 282|652 304!652 304[670 314 682 312!682 312|695 309!695 309|722 293!722 293[758 272 772 271!772 271[791 269 818 282!818 282[838 292 889 345!889 345|941 403!941 403[984 434 1024 431!1024 431[1052 429 1068 409!1068 409
[1102 373 1112 314!1112 314[1121 258 1102 217!1102 217[1085 181 1060 161!868 366[818 312 802 304!802 304|782 301!782 301[753 303 716 329!716 329[699 338 678 340!678 340[646 342 592 318!592 318|543 310!543 310[475 314 424 384!424 384[409
 405 379 408!379 408|326 399!326 399|239 388!239 388|230 388!230 388[177 392 163 451!163 451[148 516 230 554!230 554|241 562!241 562[246 572 234 580!234 580[171 625 146 654!146 654[74 732 80 827!80 827[109 749 150 692!150 692[203 625
 225 615!225 615|232 613!232 613[242 612 245 620!245 620[248 627 241 633!241 633|216 654!216 654|169 707!169 707[140 739 114 789!114 789|85 856!85 856|92 878!92 878[100 852 118 818!118 818[142 774 167 745!167 745[202 706 227 693!227 693
|232 692!232 692[242 691 243 702!243 702[244 714 230 723!230 723|184 763!184 763[144 810 98 898!98 898|100 920!100 920|133 907!133 907|130 921!130 921[63 980 103 1058!103 1058[143 1136 227 1129!227 1129|242 1127!242 1127[344 1281 478
 1354!478 1354[492 1361 490 1367!490 1367[490 1372 478 1373!478 1373[438 1377 379 1343!379 1343[393 1416 490 1469!490 1469[582 1517 665 1512!665 1512[705 1508 724 1491!724 1491|720 1493!720 1493|653 1484!653 1484[608 1473 610 1465!610
 1465|614 1463!614 1463|637 1464!637 1464|679 1464!679 1464[761 1458 861 1406!861 1406[942 1363 1002 1294!1002 1294[947 1266 923 1250!923 1250[808 1176 853 1114!853 1114[924 1018 1064 1060!1064 1060|1116 1081!1116 1081[1177 893 1123 705
!1123 705[1089 580 1002 457!1002 457[964 455 921 423!921 423|868 366!1100 413[1092 415 1084 423!1084 423[1065 444 1040 453!1040 453|1104 559!1104 559[1127 508 1129 489!1129 489[1131 457 1123 435!1123 435[1114 412 1100 413!1036 565|1013
 557!1013 557|986 531!986 531|977 524!977 524|971 531!971 531|964 546!964 546[939 589 900 600!900 600|877 596!877 596[861 589 869 585!869 585[903 575 921 542!921 542|932 525!932 525|944 508!944 508[965 491 1002 518!1002 518|1048 560!1048
 560[1054 567 1036 565!984 639[997 656 1000 685!1000 685[1004 713 993 735!993 735[984 755 969 756!969 756[955 758 942 739!942 739[930 720 928 692!928 692[924 665 934 643!934 643[942 623 957 621!957 621|958 621!958 621[971 620 984 639
!832 834|785 758!785 758[758 712 739 660!739 660[732 642 742 638!742 638|744 638!744 638[753 638 762 654!762 654[785 701 806 730!806 730[828 761 892 829!892 829|898 845!898 845|895 861!895 861|855 929!855 929[848 940 830 942!830 942|808
 938!808 938[800 938 797 932!797 932[794 925 799 918!799 918|832 867!832 867|836 851!836 851|832 834!524 453[543 461 536 465!536 465[499 481 481 521!481 521[472 539 457 598!457 598|436 600!436 600[417 596 419 589!419 589[434 529 442 508
!442 508[462 468 499 451!499 451|524 453!186 808[207 782 232 771!232 771|234 770!234 770[244 769 248 778!248 778[252 787 241 795!241 795|227 806!227 806[214 815 203 825!203 825|178 856!178 856|159 877!159 877|156 873!156 873[154 865 163
 844!163 844[173 825 186 808!239 847[247 846 251 855!251 855[254 863 247 869!247 869|234 880!234 880[221 894 221 903!221 903[221 915 210 915!210 915[198 915 198 900!198 900[198 886 211 869!211 869|234 849!234 849|239 847!538 647|539 647
!539 647[555 646 567 666!567 666[579 684 581 712!581 712[584 739 575 760!575 760[567 781 552 782!552 782[536 783 523 764!523 764[511 747 509 719!509 719[507 690 514 670!514 670[523 649 538 647!787 1111[807 1129 814 1155!814 1155[820 1180
 812 1207!812 1207[806 1226 789 1229!789 1229[772 1234 755 1224!755 1224[703 1197 731 1125!731 1125[751 1071 796 1023!796 1023|819 1025!819 1025[837 1032 832 1037!832 1037[799 1071 780 1108!780 1108|787 1111!768 1209|776 1185!776 1185
[782 1164 774 1144!774 1144|770 1133!770 1133[757 1168 763 1196!763 1196|768 1209!1327 1317[1298 1277 1216 1195!1216 1195[1133 1114 1027 1091!1027 1091|958 1079!958 1079[915 1076 894 1098!894 1098[872 1122 877 1142!877 1142[881 1155 906
 1178!906 1178[944 1216 1010 1251!1010 1251|1125 1306!1125 1306|1212 1281!1212 1281[1227 1277 1216 1292!1216 1292|1193 1309!1193 1309[1060 1346 984 1396!984 1396[928 1435 955 1472!955 1472|964 1482!964 1482|976 1491!976 1491[1008 1513
 1051 1515!1051 1515[1135 1502 1203 1474!1203 1474[1221 1467 1212 1481!1212 1481|1193 1499!1193 1499[1110 1540 1033 1545!1033 1545|1002 1549!1002 1549[1002 1599 1054 1632!1054 1632[1106 1663 1174 1666!1174 1666[1245 1670 1309 1604!1309
 1604[1366 1542 1377 1470!1377 1470[1388 1400 1327 1317"/>
                  </edges>
                </DOMShape>
              </elements>
            </DOMFrame>
            <DOMFrame index="50" duration="5" keyMode="9728">
              <elements>
                <DOMShape isFloating="true">
                  <fills>
                    <FillStyle index="1">
                      <SolidColor color="#FFFFFF"/>
                    </FillStyle>
                  </fills>
                  <edges>
                    <Edge fillStyle0="1" edges="
!1732 843|1661 845!1661 845[1638 870 1645 912!1645 912[1656 972 1690 1048!1690 1048|1752 1168!1752 1168[1791 1180 1837 1198!1837 1198[1845 1203 1828 1217!1828 1217[1813 1233 1802 1228!1802 1228|1735 1205!1735 1205|1720 1203!1720 1203
|1717 1198!1717 1198[1540 1142 1527 1223!1527 1223[1522 1255 1544 1282!1544 1282[1654 1357 1760 1384!1760 1384[1768 1386 1752 1402!1752 1402[1735 1416 1726 1414!1726 1414|1713 1411!1713 1411[1620 1388 1550 1341!1550 1341[1532 1330 1520
 1319!1520 1319|1518 1318!1518 1318[1498 1393 1591 1511!1591 1511[1626 1553 1675 1563!1675 1563[1715 1573 1774 1561!1774 1561[1848 1545 1904 1488!1904 1488[1967 1423 1947 1352!1947 1352|1901 1200!1901 1200|1812 929!1812 929[1788 872 1732
 843!1056 78[1033 49 999 31!999 31[1013 68 997 95!997 95[974 126 940 137!940 137[891 152 841 122!841 122[721 48 683 51!683 51|659 55!659 55[639 61 614 79!614 79[587 99 578 101!578 101|548 97!548 97|498 61!498 61[423 -4 397 0!397 0|390
 2!390 2[362 11 329 53!329 53|308 82!308 82|284 109!284 109[237 142 202 159!202 159[148 185 118 263!118 263[88 349 82 353!82 353[49 382 25 455!25 455[9 507 2 564!2 564[-9 664 59 798!59 798[94 865 130 912!130 912[121 823 163 746!163 746
[182 709 222 658!222 658[182 644 151 623!151 623[109 594 104 566!104 566[97 525 111 490!111 490[128 443 181 426!181 426|204 421!204 421|279 424!279 424|347 426!347 426|352 423!352 423[358 421 398 335!398 335[436 255 471 244!471 244|489
 243!489 243|530 252!530 252|569 263!569 263|618 275!618 275|652 277!652 277|664 270!664 270|686 248!686 248[716 218 732 213!732 213[750 206 782 213!782 213[807 218 870 260!870 260|936 306!936 306[988 328 1027 315!1027 315[1054 307 1068
 283!1068 283[1094 237 1088 176!1088 176[1085 116 1056 78!883 433[872 440 855 428!855 428[839 418 852 411!852 411[972 349 1077 435!1077 435[1092 447 1077 455!1077 455[1063 462 1051 451!1051 451[1010 417 970 413!970 413[931 409 883 433
!852 285[789 243 771 238!771 238|750 241!750 241[720 249 689 285!689 285[673 300 654 306!654 306|560 304!560 304|509 307!509 307[442 328 405 411!405 411[394 438 365 446!365 446|310 450!310 450|217 458!217 458|210 460!210 460[156 477 156
 542!156 542[156 611 249 630!249 630|261 636!261 636[270 644 259 655!259 655[209 711 186 752!186 752[131 850 163 944!163 944[168 866 200 790!200 790[241 707 258 694!258 694|265 690!265 690[276 687 279 694!279 694[285 702 277 709!277 709
|259 737!259 737[236 771 222 800!222 800[191 858 172 972!172 972|184 994!184 994[197 901 229 840!229 840[254 791 281 772!281 772|284 770!284 770[293 768 297 778!297 778[301 790 290 802!290 802[264 830 252 855!252 855[222 912 197 1011
!197 1011|197 1013!197 1013[205 1024 202 1035!202 1035|235 1013!235 1013|234 1028!234 1028[181 1104 240 1173!240 1173[298 1242 382 1216!382 1216|398 1210!398 1210[455 1264 513 1303!513 1303|525 1300!525 1300[532 1299 530 1314!530 1314
[609 1363 693 1386!693 1386[708 1390 709 1396!709 1396|696 1405!696 1405|654 1409!654 1409|589 1398!589 1398[620 1468 733 1498!733 1498[839 1526 920 1500!920 1500[959 1489 976 1467!976 1467|972 1469!972 1469|902 1475!902 1475[852 1475
 854 1467!854 1467|856 1464!856 1464|880 1460!880 1460|924 1450!924 1450[1004 1425 1093 1346!1093 1346|1131 1309!1131 1309|1142 1299!1142 1299[1255 1171 1275 981!1275 981[1300 763 1194 571!1194 571[1130 453 1012 347!1012 347[974 353 920
 332!920 332|852 285!1129 296[1115 275 1101 279!1101 279|1087 292!1087 292[1073 317 1049 334!1049 334|1140 426!1140 426[1151 371 1148 349!1148 349[1142 317 1129 296!1069 630[1065 655 1051 659!1051 659[1035 664 1018 648!1018 648[1002 632
 991 604!991 604[982 577 986 554!986 554[990 530 1004 525!1004 525|1006 525!1006 525[1020 521 1038 537!1038 537[1054 553 1063 580!1063 580[1073 607 1069 630!878 672|943 722!943 722|988 752!988 752|999 766!999 766|999 783!999 783|974 862
!974 862[968 877 952 883!952 883|929 884!929 884|916 879!916 879|915 865!915 865|936 805!936 805[943 786 929 771!929 771|863 704!863 704[824 664 792 616!792 616[780 598 790 594!790 594|791 593!791 593[802 591 814 605!814 605|878 672!961
 969[979 975 977 981!977 981[951 1025 940 1065!940 1065|942 1065!942 1065[992 1089 997 1147!997 1147[999 1171 987 1182!987 1182[974 1194 952 1188!952 1188[888 1171 895 1092!895 1092[901 1031 937 970!937 970|961 969!538 470[503 497 494
 541!494 541[490 562 490 626!490 626|469 629!469 629[449 625 449 616!449 616[451 550 456 528!456 528[465 483 501 457!501 457|525 458!525 458[544 466 538 470!320 854[326 863 317 875!317 875|286 912!286 912|268 949!268 949|254 975!254 975
|249 972!249 972[244 965 251 941!251 941|265 901!265 901[277 872 302 851!302 851|306 849!306 849[313 847 320 854!328 925[337 924 342 931!342 931[347 939 340 946!340 946[320 973 324 988!324 988[325 999 315 1002!315 1002[302 1006 299 990
!299 990[295 976 304 956!304 956|322 929!322 929|328 925!644 707[653 734 649 757!649 757[646 780 630 786!630 786[616 791 598 774!598 774[582 759 572 730!572 730[562 704 566 680!566 680[570 657 585 652!585 652[600 648 618 663!618 663[634
 680 644 707!936 1085[932 1117 938 1146!938 1146|943 1161!943 1161|950 1171!950 1171[957 1163 957 1144!957 1144[959 1122 947 1102!947 1102|936 1085"/>
                  </edges>
                </DOMShape>
              </elements>
            </DOMFrame>
            <DOMFrame index="55" duration="65" keyMode="9728">
              <elements>
                <DOMShape isFloating="true">
                  <fills>
                    <FillStyle index="1">
                      <SolidColor color="#FFFFFF"/>
                    </FillStyle>
                  </fills>
                  <edges>
                    <Edge fillStyle0="1" edges="
!1053 77[1030 49 997 31!997 31[1010 68 994 94!994 94[972 126 938 137!938 137[888 152 840 122!840 122[720 48 682 51!682 51|658 55!658 55[637 61 613 79!613 79|577 101!577 101|547 97!547 97[535 91 497 61!497 61[422 -4 396 0!396 0|390 2!390
 2[361 11 329 53!329 53|308 82!308 82|283 109!283 109[237 142 203 158!203 158[147 185 119 262!119 262|83 352!83 352[49 381 25 454!25 454[9 506 2 563!2 563[-9 662 59 796!59 796[94 863 130 910!130 910[120 821 163 744!163 744[182 707 221
 656!221 656[182 642 151 621!151 621[109 593 104 564!104 564[97 524 110 488!110 488[128 442 181 425!181 425|203 420!203 420|279 423!279 423[330 429 346 424!346 424|352 422!352 422|397 334!397 334[435 255 470 243!470 243|488 242!488 242
|528 251!528 251|567 262!567 262|616 274!616 274|650 276!650 276|662 269!662 269|685 248!685 248[714 217 730 212!730 212|781 213!781 213[804 217 868 260!868 260|934 305!934 305[985 327 1025 314!1025 314[1052 307 1065 282!1065 282[1091
 236 1086 175!1086 175[1082 116 1053 77!918 331|850 285!850 285[787 242 770 238!770 238|748 240!748 240[719 248 687 285!687 285[672 299 653 305!653 305|560 303!560 303|508 307!508 307[441 327 404 410!404 410[393 437 365 445!365 445|309
 449!309 449|217 457!217 457|210 459!210 459[156 476 156 540!156 540[156 610 249 628!249 628[256 630 260 635!260 635[269 642 258 654!258 654[208 709 186 750!186 750[131 847 162 942!162 942[167 864 199 788!199 788[241 705 257 692!257 692
|264 688!264 688[275 685 279 692!279 692[284 700 277 707!277 707|258 735!258 735[235 769 222 798!222 798[191 856 172 970!172 970|183 992!183 992[197 899 230 838!230 838[254 789 280 770!280 770|283 768!283 768[292 766 296 776!296 776[300
 788 289 800!289 800[264 828 252 852!252 852[222 910 196 1009!196 1009|196 1010!196 1010[205 1021 203 1032!203 1032|235 1010!235 1010|233 1026!233 1026[181 1101 239 1170!239 1170[298 1239 381 1213!381 1213|397 1207!397 1207[538 1340 691
 1383!691 1383[707 1387 707 1393!707 1393[707 1398 695 1402!695 1402|653 1405!653 1405|587 1394!587 1394[619 1464 731 1494!731 1494[836 1522 918 1496!918 1496[956 1485 973 1463!973 1463|969 1465!969 1465|900 1471!900 1471[850 1471 851
 1463!851 1463[851 1460 854 1460!854 1460|878 1456!878 1456|922 1446!922 1446[1002 1421 1090 1343!1090 1343[1247 1207 1272 978!1272 978[1297 761 1191 569!1191 569[1127 451 1010 346!1010 346[972 352 918 331!909 378|919 378!919 378|1010
 403!1010 403[1019 407 1020 410!1020 410|1012 416!1012 416|929 436!929 436|911 433!911 433[902 428 902 417!902 417|898 396!898 396[897 380 909 378!1137 425[1148 371 1145 349!1145 349[1139 317 1126 295!1126 295[1113 274 1098 278!1098 278
[1089 282 1084 292!1084 292[1071 317 1047 334!1047 334|1137 425!1042 653[1027 658 1010 642!1010 642[993 626 983 599!983 599[974 572 978 549!978 549[981 527 996 522!996 522[1010 517 1028 532!1028 532[1044 547 1054 574!1054 574[1064 601
 1060 624!1060 624[1057 647 1042 652!1042 652|1042 653!938 716|981 745!981 745[998 757 993 776!993 776|970 854!970 854[964 869 949 874!949 874|926 875!926 875|913 872!913 872[909 866 912 858!912 858|932 798!932 798|932 780!932 780|924
 764!924 764|858 700!858 700[819 660 787 614!787 614[775 597 785 592!785 592|786 592!786 592[796 589 809 603!809 603|873 669!873 669|938 716"/>
                    <Edge fillStyle1="1" edges="
!1147 867[1142 867 1146 877!1146 877|1152 891!1152 891|1150 907!1150 907|1138 919!1138 919[1056 965 990 984!990 984|962 992!962 992|827 997!827 997|743 993!743 993|726 988!726 988[716 981 716 973!716 973|719 938!719 938[721 927 714 928
!714 928|707 933!707 933|630 1032!630 1032[617 1048 626 1065!626 1065|670 1150!670 1150|679 1158!679 1158|686 1148!686 1148|672 1104!672 1104[677 1091 690 1087!690 1087|700 1085!700 1085|803 1116!803 1116[920 1143 981 1126!981 1126|982
 1126!982 1126[1042 1108 1106 1049!1106 1049|1157 994!1157 994|1163 992!1163 992[1175 987 1181 1003!1181 1003|1183 1013!1183 1013|1189 1021!1189 1021|1195 1012!1195 1012|1218 934!1218 934[1223 914 1205 904!1205 904|1157 869!1157 869|1147
 867!1149 937[1170 930 1171 949!1171 949[1171 969 1158 976!1158 976|1049 1054!1049 1054[1028 1068 987 1080!987 1080|885 1097!885 1097|782 1082!782 1082|714 1069!714 1069|694 1059!694 1059[683 1049 692 1036!692 1036[702 1023 716 1019!716
 1019|741 1016!741 1016|819 1021!819 1021|958 1014!958 1014|986 1006!986 1006[1061 984 1145 938!1145 938|1149 937"/>
                    <Edge fillStyle0="1" edges="
!513 474[526 471 531 480!531 480[572 505 569 517!569 517[545 533 520 556!520 556[471 613 460 615!460 615|459 615!459 615[445 593 474 534!474 534|504 480!504 480[509 475 513 474!319 852[325 861 316 872!316 872|285 910!285 910|268 947!268
 947|253 972!253 972|248 970!248 970[244 962 250 938!250 938|264 899!264 899[277 870 302 849!302 849|305 847!305 847[313 845 319 852!321 926|327 923!327 923[336 921 341 928!341 928[346 936 340 944!340 944[319 971 323 985!323 985[325 997
 314 999!314 999[302 1004 298 987!298 987[294 974 304 953!304 953|321 926!642 705[651 732 648 755!648 755[644 778 628 784!628 784[614 789 597 772!597 772[580 757 571 728!571 728[562 702 565 679!565 679[569 655 584 650!584 650[599 646
 616 662!616 662[633 678 642 705!1069 1143|1064 1153!1064 1153|1036 1180!1036 1180[1025 1190 1011 1193!1011 1193|987 1198!987 1198|976 1198!976 1198|959 1192!959 1192|951 1179!951 1179[949 1162 968 1158!968 1158[971 1156 971 1157!971
 1157|1058 1143!1058 1143|1069 1143"/>
                  </edges>
                </DOMShape>
              </elements>
            </DOMFrame>
          </frames>
        </DOMLayer>
      </layers>
    </DOMTimeline>
  </timeline>
</DOMSymbolItem>